ftbqcache/__init__.py
ftbqcache/py.typed
ftbqcache-0.1.0.dist-info/METADATA
ftbqcache-0.1.0.dist-info/WHEEL
ftbqcache-0.1.0.dist-info/RECORD
