Metadata-Version: 2.4
Name: ftbqcache
Version: 0.1.0
Summary: Add your description here
Author-email: George Fraser <george.w.fraser@gmail.com>
Requires-Python: >=3.10
Requires-Dist: db-dtypes>=1.4.3
Requires-Dist: google-cloud-bigquery-storage>=2.32.0
Requires-Dist: google-cloud-bigquery>=3.34.0
Requires-Dist: pandas>=2.3.1
Requires-Dist: pyarrow>=20.0.0
